triex/__init__.py
triex/triex.py
triex-0.1.2.dist-info/entry_points.txt
triex-0.1.2.dist-info/WHEEL
triex-0.1.2.dist-info/METADATA
triex-0.1.2.dist-info/RECORD
